running_results_fetcher/__init__.py
running_results_fetcher/__main__.py
running_results_fetcher/app.py
running_results_fetcher/enduhube_page_parser.py
running_results_fetcher/helpers.py
running_results_fetcher/race_result.py
running_results_fetcher/runner.py
running_results_fetcher/spider.py
running_results_fetcher/spider_config.py
running_results_fetcher/spider_runner.py
running_results_fetcher/stats.py
running_results_fetcher-0.2.2.dist-info/AUTHORS.rst
running_results_fetcher-0.2.2.dist-info/LICENSE
running_results_fetcher-0.2.2.dist-info/METADATA
running_results_fetcher-0.2.2.dist-info/WHEEL
running_results_fetcher-0.2.2.dist-info/entry_points.txt
running_results_fetcher-0.2.2.dist-info/top_level.txt
running_results_fetcher-0.2.2.dist-info/RECORD
