Metadata-Version: 2.1
Name: running-results-fetcher
Version: 0.2.2
Summary: Running Results Fetcher download
Home-page: https://github.com/mojek/running_results_fetcher
Author: Michal Mojek
Author-email: m.mojek@gmail.com
License: MIT license
Keywords: running_results_fetcher
Platform: UNKNOWN
Classifier: Development Status :: 2 - Pre-Alpha
Classifier: Intended Audience :: Developers
Classifier: License :: OSI Approved :: MIT License
Classifier: Natural Language :: English
Classifier: Programming Language :: Python :: 2
Classifier: Programming Language :: Python :: 2.7
Classifier: Programming Language :: Python :: 3
Classifier: Programming Language :: Python :: 3.4
Classifier: Programming Language :: Python :: 3.5
Classifier: Programming Language :: Python :: 3.6
Classifier: Programming Language :: Python :: 3.7
Requires-Dist: Click (>=6.0)
Requires-Dist: Scrapy (>=1.6)
Requires-Dist: Beautifulsoup4
